odoo/addons/shopinvader_customer_price_pricelist_cache/README.rst
odoo/addons/shopinvader_customer_price_pricelist_cache/__init__.py
odoo/addons/shopinvader_customer_price_pricelist_cache/__manifest__.py
odoo/addons/shopinvader_customer_price_pricelist_cache/i18n/shopinvader_customer_price_pricelist_cache.pot
odoo/addons/shopinvader_customer_price_pricelist_cache/readme/CONTRIBUTORS.rst
odoo/addons/shopinvader_customer_price_pricelist_cache/readme/DESCRIPTION.rst
odoo/addons/shopinvader_customer_price_pricelist_cache/services/__init__.py
odoo/addons/shopinvader_customer_price_pricelist_cache/services/customer_price.py
odoo/addons/shopinvader_customer_price_pricelist_cache/static/description/index.html
odoo/addons/shopinvader_customer_price_pricelist_cache/tests/tests/__init__.py
odoo/addons/shopinvader_customer_price_pricelist_cache/tests/tests/test_customer_price.py
odoo14_addon_shopinvader_customer_price_pricelist_cache-14.0.1.0.1.dev2.dist-info/METADATA
odoo14_addon_shopinvader_customer_price_pricelist_cache-14.0.1.0.1.dev2.dist-info/WHEEL
odoo14_addon_shopinvader_customer_price_pricelist_cache-14.0.1.0.1.dev2.dist-info/top_level.txt
odoo14_addon_shopinvader_customer_price_pricelist_cache-14.0.1.0.1.dev2.dist-info/RECORD
