Metadata-Version: 2.1
Name: odoo14-addon-shopinvader_customer_price_pricelist_cache
Version: 14.0.1.0.1.dev2
Summary: Glue module between shopinvader_customer_price and pricelist_cache
Home-page: https://github.com/shopinvader/odoo-shopinvader
Author: Camptocamp SA, Odoo Community Association (OCA)
Author-email: support@odoo-community.org
License: AGPL-3
Classifier: Programming Language :: Python
Classifier: Framework :: Odoo
Classifier: Framework :: Odoo :: 14.0
Classifier: License :: OSI Approved :: GNU Affero General Public License v3
Requires-Python: >=3.6
Requires-Dist: odoo14-addon-pricelist-cache
Requires-Dist: odoo14-addon-shopinvader-customer-price
Requires-Dist: odoo<14.1dev,>=14.0a
